Metadata-Version: 2.1
Name: py-imu-mpu6050
Version: 0.2
Summary:  Inertial Measurement Unit (IMU) Driver based on on the MPU6050
Home-page: https://github.com/romybompart/py_imu_mpu6050
Author: Romy Bompart
Author-email: romybompart@gmail.com
License: Creative Commons Zero v1.0 Universal
Keywords: IMU MPU6050 i2c hardware python jetsonnano raspberrypi adafruit
Platform: UNKNOWN
Classifier: Development Status :: 3 - Alpha
Classifier: Intended Audience :: Developers
Classifier: Topic :: Software Development :: Libraries :: Python Modules
Classifier: Topic :: System :: Hardware
Classifier: License :: OSI Approved :: Common Development and Distribution License 1.0 (CDDL-1.0)
Classifier: Programming Language :: Python :: 3
Classifier: Programming Language :: Python :: 3.4
Classifier: Programming Language :: Python :: 3.5
Classifier: Programming Language :: Python :: 3.6
